pptx_template/__init__.py
pptx_template/chart.py
pptx_template/cli.py
pptx_template/core.py
pptx_template/pptx_util.py
pptx_template/pyel.py
pptx_template/table.py
pptx_template/text.py
pptx_template/xlsx_model.py
pptx_template-0.2.9.dist-info/LICENSE
pptx_template-0.2.9.dist-info/METADATA
pptx_template-0.2.9.dist-info/WHEEL
pptx_template-0.2.9.dist-info/entry_points.txt
pptx_template-0.2.9.dist-info/top_level.txt
pptx_template-0.2.9.dist-info/RECORD
