Metadata-Version: 2.1
Name: pptx-template
Version: 0.2.9
Summary: The PowerPoint presentation builder using template.pptx and data(json and csv)
Home-page: http://github.com/m3dev/pptx-template
Author: Reki Murakami
Author-email: reki2000@gmail.com
License: Apache-2.0
Keywords: powerpoint,ppt,pptx
Platform: UNKNOWN
Classifier: Development Status :: 3 - Alpha
Classifier: Topic :: Utilities
Classifier: Programming Language :: Python :: 2
Classifier: Programming Language :: Python :: 2.7
Classifier: Programming Language :: Python :: 3
Classifier: Programming Language :: Python :: 3.5
Classifier: License :: OSI Approved :: Apache Software License
Classifier: Operating System :: OS Independent
Requires-Dist: python-pptx (==0.6.6)
Requires-Dist: pandas (<=0.24.0,>=0.22)
Requires-Dist: openpyxl (>=2.4.7)
